ultimate_sol/__init__.py
ultimate_sol/dexscreener.py
ultimate_sol/jupiter.py
ultimate_sol/metadata.py
ultimate_sol/sol.py
ultimate_sol/solana_fm.py
ultimate_sol-0.0.3.dist-info/METADATA
ultimate_sol-0.0.3.dist-info/WHEEL
ultimate_sol-0.0.3.dist-info/licenses/LICENSE
ultimate_sol-0.0.3.dist-info/RECORD
