Metadata-Version: 2.3
Name: ultimate_sol
Version: 0.0.3
Summary: This library contains a set of functions for interacting with Solana blockchain, as well as some third-party APIs such as Jupiter, DexScreener, etc.
Project-URL: Homepage, https://github.com/smbd0x
Author-email: smbd0x <smbd0x@rambler.ru>
License-File: LICENSE
Classifier: License :: OSI Approved :: MIT License
Classifier: Operating System :: OS Independent
Classifier: Programming Language :: Python :: 3
Requires-Python: >=3.6.0
Requires-Dist: base58==2.1.1
Requires-Dist: construct==2.10.68
Requires-Dist: httpx==0.27.2
Requires-Dist: solana==0.35.0
Requires-Dist: solders==0.21.0
